xtools/__init__.py
xtools/base.py
xtools/exceptions.py
xtools/page.py
xtools/project.py
xtools/py.typed
xtools/quote.py
xtools/user.py
xtools-0.2.0.dist-info/LICENSE
xtools-0.2.0.dist-info/METADATA
xtools-0.2.0.dist-info/WHEEL
xtools-0.2.0.dist-info/RECORD
