Metadata-Version: 2.1
Name: xtools
Version: 0.2.0
Summary: XTools API wrapper
Home-page: https://github.com/bfontaine/xtools
Author: Baptiste Fontaine
Author-email: b@ptistefontaine.fr
Requires-Python: >=3.8,<4.0
Classifier: Development Status :: 5 - Production/Stable
Classifier: Intended Audience :: Developers
Classifier: License :: OSI Approved :: MIT License
Classifier: Operating System :: OS Independent
Classifier: Programming Language :: Python :: 3
Classifier: Programming Language :: Python :: 3.8
Classifier: Programming Language :: Python :: 3.9
Classifier: Programming Language :: Python :: 3.10
Classifier: Programming Language :: Python :: 3.11
Classifier: Programming Language :: Python :: 3
Requires-Dist: requests (>=2.28.2,<3.0.0)
